<annotation>
	<folder>202204152318 (2022-4-15 23-31-01)</folder>
	<filename>202204152318 096.jpg</filename>
	<path>E:\202204152318 (2022-4-15 23-31-01)\202204152318 096.jpg</path>
	<source>
		<database>Unknown</database>
	</source>
	<size>
		<width>2160</width>
		<height>1080</height>
		<depth>3</depth>
	</size>
	<segmented>0</segmented>
	<object>
		<name>m</name>
		<pose>Unspecified</pose>
		<truncated>0</truncated>
		<difficult>0</difficult>
		<bndbox>
			<xmin>1114</xmin>
			<ymin>443</ymin>
			<xmax>1296</xmax>
			<ymax>675</ymax>
		</bndbox>
	</object>
	<object>
		<name>s</name>
		<pose>Unspecified</pose>
		<truncated>0</truncated>
		<difficult>0</difficult>
		<bndbox>
			<xmin>899</xmin>
			<ymin>619</ymin>
			<xmax>1094</xmax>
			<ymax>1039</ymax>
		</bndbox>
	</object>
	<object>
		<name>s</name>
		<pose>Unspecified</pose>
		<truncated>0</truncated>
		<difficult>0</difficult>
		<bndbox>
			<xmin>1456</xmin>
			<ymin>645</ymin>
			<xmax>1588</xmax>
			<ymax>1009</ymax>
		</bndbox>
	</object>
</annotation>
