<annotation>
	<folder>202204152318 (2022-4-15 23-31-01)</folder>
	<filename>202204152318 124.jpg</filename>
	<path>E:\202204152318 (2022-4-15 23-31-01)\202204152318 124.jpg</path>
	<source>
		<database>Unknown</database>
	</source>
	<size>
		<width>2160</width>
		<height>1080</height>
		<depth>3</depth>
	</size>
	<segmented>0</segmented>
	<object>
		<name>m</name>
		<pose>Unspecified</pose>
		<truncated>0</truncated>
		<difficult>0</difficult>
		<bndbox>
			<xmin>1064</xmin>
			<ymin>455</ymin>
			<xmax>1278</xmax>
			<ymax>696</ymax>
		</bndbox>
	</object>
	<object>
		<name>s</name>
		<pose>Unspecified</pose>
		<truncated>0</truncated>
		<difficult>0</difficult>
		<bndbox>
			<xmin>885</xmin>
			<ymin>621</ymin>
			<xmax>1107</xmax>
			<ymax>958</ymax>
		</bndbox>
	</object>
	<object>
		<name>s</name>
		<pose>Unspecified</pose>
		<truncated>0</truncated>
		<difficult>0</difficult>
		<bndbox>
			<xmin>1314</xmin>
			<ymin>633</ymin>
			<xmax>1509</xmax>
			<ymax>896</ymax>
		</bndbox>
	</object>
</annotation>
