<annotation>
	<folder>VID20220415082933 (2022-4-15 11-10-29)</folder>
	<filename>VID20220415082933 12.jpg</filename>
	<path>E:\图片4.15\VID20220415082933 (2022-4-15 11-10-29)\VID20220415082933 12.jpg</path>
	<source>
		<database>Unknown</database>
	</source>
	<size>
		<width>1080</width>
		<height>1920</height>
		<depth>3</depth>
	</size>
	<segmented>0</segmented>
	<object>
		<name>m</name>
		<pose>Unspecified</pose>
		<truncated>0</truncated>
		<difficult>0</difficult>
		<bndbox>
			<xmin>468</xmin>
			<ymin>489</ymin>
			<xmax>661</xmax>
			<ymax>664</ymax>
		</bndbox>
	</object>
	<object>
		<name>s</name>
		<pose>Unspecified</pose>
		<truncated>0</truncated>
		<difficult>0</difficult>
		<bndbox>
			<xmin>435</xmin>
			<ymin>1051</ymin>
			<xmax>528</xmax>
			<ymax>1245</ymax>
		</bndbox>
	</object>
	<object>
		<name>s</name>
		<pose>Unspecified</pose>
		<truncated>0</truncated>
		<difficult>0</difficult>
		<bndbox>
			<xmin>632</xmin>
			<ymin>565</ymin>
			<xmax>733</xmax>
			<ymax>777</ymax>
		</bndbox>
	</object>
</annotation>
