<annotation>
	<folder>VID20220415082536 (2022-4-15 11-10-29)</folder>
	<filename>VID20220415082536 13.jpg</filename>
	<path>E:\图片4.15\VID20220415082536 (2022-4-15 11-10-29)\VID20220415082536 13.jpg</path>
	<source>
		<database>Unknown</database>
	</source>
	<size>
		<width>1080</width>
		<height>1920</height>
		<depth>3</depth>
	</size>
	<segmented>0</segmented>
	<object>
		<name>m</name>
		<pose>Unspecified</pose>
		<truncated>0</truncated>
		<difficult>0</difficult>
		<bndbox>
			<xmin>537</xmin>
			<ymin>593</ymin>
			<xmax>666</xmax>
			<ymax>712</ymax>
		</bndbox>
	</object>
	<object>
		<name>s</name>
		<pose>Unspecified</pose>
		<truncated>0</truncated>
		<difficult>0</difficult>
		<bndbox>
			<xmin>510</xmin>
			<ymin>833</ymin>
			<xmax>568</xmax>
			<ymax>957</ymax>
		</bndbox>
	</object>
	<object>
		<name>s</name>
		<pose>Unspecified</pose>
		<truncated>0</truncated>
		<difficult>0</difficult>
		<bndbox>
			<xmin>609</xmin>
			<ymin>828</ymin>
			<xmax>675</xmax>
			<ymax>991</ymax>
		</bndbox>
	</object>
</annotation>
