<annotation verified="yes">
	<folder>VID20220413101358 (2022-4-13 20-16-37)</folder>
	<filename>VID20220413101358 05.jpg</filename>
	<path>D:\图片库\图片库30\VID20220413101358 (2022-4-13 20-16-37)\VID20220413101358 05.jpg</path>
	<source>
		<database>Unknown</database>
	</source>
	<size>
		<width>1080</width>
		<height>1920</height>
		<depth>3</depth>
	</size>
	<segmented>0</segmented>
	<object>
		<name>s</name>
		<pose>Unspecified</pose>
		<truncated>0</truncated>
		<difficult>0</difficult>
		<bndbox>
			<xmin>627</xmin>
			<ymin>521</ymin>
			<xmax>693</xmax>
			<ymax>597</ymax>
		</bndbox>
	</object>
	<object>
		<name>s</name>
		<pose>Unspecified</pose>
		<truncated>0</truncated>
		<difficult>0</difficult>
		<bndbox>
			<xmin>717</xmin>
			<ymin>544</ymin>
			<xmax>776</xmax>
			<ymax>597</ymax>
		</bndbox>
	</object>
	<object>
		<name>m</name>
		<pose>Unspecified</pose>
		<truncated>0</truncated>
		<difficult>0</difficult>
		<bndbox>
			<xmin>669</xmin>
			<ymin>492</ymin>
			<xmax>744</xmax>
			<ymax>539</ymax>
		</bndbox>
	</object>
</annotation>
