<annotation verified="yes">
	<folder>VID20220413101157 (2022-4-13 20-16-37)</folder>
	<filename>VID20220413101157 07.jpg</filename>
	<path>D:\图片库\图片库30\VID20220413101157 (2022-4-13 20-16-37)\VID20220413101157 07.jpg</path>
	<source>
		<database>Unknown</database>
	</source>
	<size>
		<width>1080</width>
		<height>1920</height>
		<depth>3</depth>
	</size>
	<segmented>0</segmented>
	<object>
		<name>m</name>
		<pose>Unspecified</pose>
		<truncated>0</truncated>
		<difficult>0</difficult>
		<bndbox>
			<xmin>468</xmin>
			<ymin>504</ymin>
			<xmax>570</xmax>
			<ymax>580</ymax>
		</bndbox>
	</object>
	<object>
		<name>s</name>
		<pose>Unspecified</pose>
		<truncated>0</truncated>
		<difficult>0</difficult>
		<bndbox>
			<xmin>323</xmin>
			<ymin>903</ymin>
			<xmax>405</xmax>
			<ymax>955</ymax>
		</bndbox>
	</object>
	<object>
		<name>s</name>
		<pose>Unspecified</pose>
		<truncated>0</truncated>
		<difficult>0</difficult>
		<bndbox>
			<xmin>595</xmin>
			<ymin>861</ymin>
			<xmax>672</xmax>
			<ymax>943</ymax>
		</bndbox>
	</object>
</annotation>
