<annotation>
	<folder>scissors</folder>
	<filename>1TU0AAG8YAGE.jpg</filename>
	<path>D:\新建文件夹 (2)\data\train\scissors\1TU0AAG8YAGE.jpg</path>
	<source>
		<database>Unknown</database>
	</source>
	<size>
		<width>512</width>
		<height>512</height>
		<depth>3</depth>
	</size>
	<segmented>0</segmented>
	<object>
		<name>ss114</name>
		<pose>Unspecified</pose>
		<truncated>0</truncated>
		<difficult>0</difficult>
		<bndbox>
			<xmin>17</xmin>
			<ymin>8</ymin>
			<xmax>498</xmax>
			<ymax>479</ymax>
		</bndbox>
	</object>
</annotation>
