<annotation>
	<folder>scissors</folder>
	<filename>V5M80PKOOA47.jpg</filename>
	<path>D:\新建文件夹 (2)\data\test\scissors\V5M80PKOOA47.jpg</path>
	<source>
		<database>Unknown</database>
	</source>
	<size>
		<width>512</width>
		<height>512</height>
		<depth>3</depth>
	</size>
	<segmented>0</segmented>
	<object>
		<name>s191</name>
		<pose>Unspecified</pose>
		<truncated>0</truncated>
		<difficult>0</difficult>
		<bndbox>
			<xmin>36</xmin>
			<ymin>102</ymin>
			<xmax>471</xmax>
			<ymax>407</ymax>
		</bndbox>
	</object>
</annotation>
